README.md
setup.py
demo/__init__.py
renjiyunpackagedemo.egg-info/PKG-INFO
renjiyunpackagedemo.egg-info/SOURCES.txt
renjiyunpackagedemo.egg-info/dependency_links.txt
renjiyunpackagedemo.egg-info/top_level.txt