Metadata-Version: 2.1
Name: renjiyunpackagedemo
Version: 0.1
Summary: just a package demo
Home-page: UNKNOWN
Author: renjiyun
Author-email: wozaijixu@msn.cn
License: UNKNOWN
Platform: UNKNOWN
Classifier: Programming Language :: Python :: 3
Classifier: License :: OSI Approved :: MIT License
Classifier: Operating System :: OS Independent
